pfdicom_tagSub/__init__.py
pfdicom_tagSub/__main__.py
pfdicom_tagSub/pfdicom_tagSub.py
pfdicom_tagSub-3.1.0.dist-info/LICENSE
pfdicom_tagSub-3.1.0.dist-info/METADATA
pfdicom_tagSub-3.1.0.dist-info/WHEEL
pfdicom_tagSub-3.1.0.dist-info/entry_points.txt
pfdicom_tagSub-3.1.0.dist-info/top_level.txt
pfdicom_tagSub-3.1.0.dist-info/RECORD
