Metadata-Version: 2.1
Name: pfdicom-tagSub
Version: 3.1.0
Summary: Process DICOM tags and performs substitutions -- part of the pf* family.
Home-page: https://github.com/FNNDSC/pfdicom_tagSub
Author: FNNDSC
Author-email: dev@babymri.org
License: MIT
License-File: LICENSE
Requires-Dist: pfdicom
